rtorch/__init__.py
rtorch/main.py
rtorch-0.0.3.dist-info/LICENSE
rtorch-0.0.3.dist-info/METADATA
rtorch-0.0.3.dist-info/WHEEL
rtorch-0.0.3.dist-info/RECORD
